imagestack_svg/__init__.py
imagestack_svg/helpers.py
imagestack_svg/imagecreator.py
imagestack_svg/imageresolve.py
imagestack_svg/imagestack.py
imagestack_svg/loaders.py
imagestack_svg-1.1.1.dist-info/LICENSE
imagestack_svg-1.1.1.dist-info/METADATA
imagestack_svg-1.1.1.dist-info/WHEEL
imagestack_svg-1.1.1.dist-info/top_level.txt
imagestack_svg-1.1.1.dist-info/RECORD
