Metadata-Version: 2.1
Name: imagestack-svg
Version: 1.1.1
Summary: Create Images by Stacking them
Home-page: https://github.com/skillor/imagestack-svg-python
Author: skillor
Author-email: skillor@gmx.net
License: MIT
Keywords: image,imagestack,imagestack-svg,imagestack_svg,svg
Platform: UNKNOWN
Classifier: Programming Language :: Python :: 3 :: Only
Classifier: Programming Language :: Python :: 3.9
Classifier: Topic :: Multimedia :: Graphics
Requires-Python: >=3
Requires-Dist: PySide2>=5.15.2.1
Requires-Dist: Jinja2>=2.11.3
Requires-Dist: requests>=2.25
Requires-Dist: Markupsafe>=2.0.1
Requires-Dist: lxml>=4.6.3
Requires-Dist: defusedxml>=0.7.1
